lpa/output/__init__.py
lpa/output/analyze.py
lpa/output/collect.py
lpa/output/filters.py
lpa/output/models.py
lpa_output-0.9.10.dist-info/LICENSE.txt
lpa_output-0.9.10.dist-info/METADATA
lpa_output-0.9.10.dist-info/WHEEL
lpa_output-0.9.10.dist-info/top_level.txt
lpa_output-0.9.10.dist-info/RECORD
