Metadata-Version: 2.1
Name: lpa-output
Version: 0.9.10
Summary: Tools for the analysis of X-ray diffraction simulation output.
Home-page: https://github.com/DunstanBecht/lpa-output
Author: Dunstan Becht
Author-email: dunstan@becht.network
License: UNKNOWN
Project-URL: Bug Tracker, https://github.com/DunstanBecht/lpa-output/issues
Platform: UNKNOWN
Classifier: Programming Language :: Python :: 3
Classifier: License :: CC0 1.0 Universal (CC0 1.0) Public Domain Dedication
Classifier: Operating System :: OS Independent
Classifier: Topic :: Scientific/Engineering :: Physics
License-File: LICENSE.txt
Requires-Dist: numpy
Requires-Dist: matplotlib
Requires-Dist: beartype
Requires-Dist: scipy
